pypasteee/__init__.py
pypasteee/paste.py
pypasteee/pasteee.py
pypasteee/section.py
pypasteee-0.0.2.dist-info/licenses/LICENSE
pypasteee-0.0.2.dist-info/METADATA
pypasteee-0.0.2.dist-info/WHEEL
pypasteee-0.0.2.dist-info/top_level.txt
pypasteee-0.0.2.dist-info/RECORD
