Metadata-Version: 2.4
Name: pypasteee
Version: 0.0.2
Summary: A simple API wrapper for paste.ee 
Author-email: m4kyu <m4kyu@proton.me>
License-Expression: MIT
Project-URL: Homepage, https://github.com/m4kyu/pypasteee
Project-URL: Issues, https://github.com/m4kyu/pypasteee/issues
Classifier: Programming Language :: Python :: 3
Classifier: Operating System :: OS Independent
Requires-Python: >=3.9
License-File: LICENSE
Requires-Dist: requests<3.0.0,>=2.0.0
Dynamic: license-file
